my_Quran/QuoranDb.py
my_Quran/__init__.py
my_Quran/fullquranDb.db
my_Quran/main.py
my_Quran-0.1.0.dist-info/LICENSE.txt
my_Quran-0.1.0.dist-info/METADATA
my_Quran-0.1.0.dist-info/WHEEL
my_Quran-0.1.0.dist-info/entry_points.txt
my_Quran-0.1.0.dist-info/top_level.txt
my_Quran-0.1.0.dist-info/RECORD
