Metadata-Version: 2.1
Name: my-Quran
Version: 0.1.0
Summary: A Tkinter application to read and search the Quran.
Home-page: https://github.com/isaiaholad/my_Quran
Author: Isaiah Olad
Author-email: isaiaholad@gmail.com
Classifier: Programming Language :: Python :: 3
Classifier: License :: OSI Approved :: MIT License
Classifier: Operating System :: OS Independent
Requires-Python: >=3.6
License-File: LICENSE.txt
Requires-Dist: tkinter
Requires-Dist: pillow
